setup.py
Embedly.egg-info/PKG-INFO
Embedly.egg-info/SOURCES.txt
Embedly.egg-info/dependency_links.txt
Embedly.egg-info/requires.txt
Embedly.egg-info/top_level.txt
Embedly.egg-info/zip-safe
embedly/__init__.py
embedly/client.py
embedly/models.py
embedly/py3_utils.py
embedly/tests.py