Metadata-Version: 1.0
Name: Embedly
Version: 0.5.0
Summary: Python Library for Embedly
Home-page: https://github.com/embedly/embedly-python
Author: Embed.ly, Inc.
Author-email: support@embed.ly
License: 
Platform: UNKNOWN
Classifier: Development Status :: 5 - Production/Stable
Classifier: Intended Audience :: Developers
Classifier: Natural Language :: English
Classifier: License :: OSI Approved :: BSD License
Classifier: Operating System :: OS Independent
Classifier: Programming Language :: Python
Classifier: Programming Language :: Python :: 2.6
Classifier: Programming Language :: Python :: 2.7
Classifier: Programming Language :: Python :: 3.2
Classifier: Programming Language :: Python :: 3.3
